{
  "id": "2c28330d-1647-407e-84dd-cfbb7e238f21",
  "prevId": "6ca51bc4-5ee1-4e3b-b29a-d8caf1bfb741",
  "version": "7",
  "dialect": "postgresql",
  "tables": {
    "public.cliente": {
      "name": "cliente",
      "schema": "",
      "columns": {
        "chave": {
          "name": "chave",
          "type": "varchar",
          "primaryKey": true,
          "notNull": true
        },
        "geo": {
          "name": "geo",
          "type": "varchar",
          "primaryKey": false,
          "notNull": false
        },
        "unb": {
          "name": "unb",
          "type": "integer",
          "primaryKey": false,
          "notNull": true
        },
        "cod_pdv": {
          "name": "cod_pdv",
          "type": "integer",
          "primaryKey": false,
          "notNull": true
        },
        "comercial": {
          "name": "comercial",
          "type": "varchar",
          "primaryKey": false,
          "notNull": false
        },
        "operação": {
          "name": "operação",
          "type": "varchar",
          "primaryKey": false,
          "notNull": false
        },
        "tipo_operação": {
          "name": "tipo_operação",
          "type": "varchar",
          "primaryKey": false,
          "notNull": false
        },
        "gv": {
          "name": "gv",
          "type": "integer",
          "primaryKey": false,
          "notNull": false
        },
        "setor": {
          "name": "setor",
          "type": "integer",
          "primaryKey": false,
          "notNull": false
        },
        "latitude": {
          "name": "latitude",
          "type": "double precision",
          "primaryKey": false,
          "notNull": false
        },
        "longitude": {
          "name": "longitude",
          "type": "double precision",
          "primaryKey": false,
          "notNull": false
        },
        "NGE": {
          "name": "NGE",
          "type": "varchar",
          "primaryKey": false,
          "notNull": false
        },
        "segmentação_primária": {
          "name": "segmentação_primária",
          "type": "varchar",
          "primaryKey": false,
          "notNull": false
        },
        "nome_fantasia": {
          "name": "nome_fantasia",
          "type": "varchar",
          "primaryKey": false,
          "notNull": false
        },
        "documento": {
          "name": "documento",
          "type": "varchar",
          "primaryKey": false,
          "notNull": false
        },
        "status": {
          "name": "status",
          "type": "varchar",
          "primaryKey": false,
          "notNull": false
        },
        "data_cadastro": {
          "name": "data_cadastro",
          "type": "timestamp",
          "primaryKey": false,
          "notNull": false
        },
        "ultima_compra": {
          "name": "ultima_compra",
          "type": "timestamp",
          "primaryKey": false,
          "notNull": false
        }
      },
      "indexes": {},
      "foreignKeys": {},
      "compositePrimaryKeys": {},
      "uniqueConstraints": {}
    },
    "public.cliente_direta": {
      "name": "cliente_direta",
      "schema": "",
      "columns": {
        "eg": {
          "name": "eg",
          "type": "varchar",
          "primaryKey": true,
          "notNull": true
        },
        "eg_dashed": {
          "name": "eg_dashed",
          "type": "varchar",
          "primaryKey": false,
          "notNull": false
        },
        "cnpj": {
          "name": "cnpj",
          "type": "varchar",
          "primaryKey": false,
          "notNull": false
        },
        "rede_uf": {
          "name": "rede_uf",
          "type": "varchar",
          "primaryKey": false,
          "notNull": false
        },
        "site_rede": {
          "name": "site_rede",
          "type": "varchar",
          "primaryKey": false,
          "notNull": false
        },
        "nome_fantasia": {
          "name": "nome_fantasia",
          "type": "varchar",
          "primaryKey": false,
          "notNull": false
        },
        "cod_operacao": {
          "name": "cod_operacao",
          "type": "varchar",
          "primaryKey": false,
          "notNull": false
        },
        "site": {
          "name": "site",
          "type": "varchar",
          "primaryKey": false,
          "notNull": false
        },
        "uf": {
          "name": "uf",
          "type": "varchar",
          "primaryKey": false,
          "notNull": false
        },
        "cidade": {
          "name": "cidade",
          "type": "varchar",
          "primaryKey": false,
          "notNull": false
        },
        "cod_rede": {
          "name": "cod_rede",
          "type": "varchar",
          "primaryKey": false,
          "notNull": false
        },
        "rede": {
          "name": "rede",
          "type": "varchar",
          "primaryKey": false,
          "notNull": false
        },
        "gn": {
          "name": "gn",
          "type": "varchar",
          "primaryKey": false,
          "notNull": false
        },
        "sn": {
          "name": "sn",
          "type": "varchar",
          "primaryKey": false,
          "notNull": false
        },
        "le": {
          "name": "le",
          "type": "varchar",
          "primaryKey": false,
          "notNull": false
        },
        "coordenador_trade": {
          "name": "coordenador_trade",
          "type": "varchar",
          "primaryKey": false,
          "notNull": false
        },
        "inplant": {
          "name": "inplant",
          "type": "varchar",
          "primaryKey": false,
          "notNull": false
        },
        "gc": {
          "name": "gc",
          "type": "varchar",
          "primaryKey": false,
          "notNull": false
        },
        "gc_oeste": {
          "name": "gc_oeste",
          "type": "varchar",
          "primaryKey": false,
          "notNull": false
        },
        "gn_sistema": {
          "name": "gn_sistema",
          "type": "varchar",
          "primaryKey": false,
          "notNull": false
        },
        "sn_sistema": {
          "name": "sn_sistema",
          "type": "varchar",
          "primaryKey": false,
          "notNull": false
        },
        "le_sistema": {
          "name": "le_sistema",
          "type": "varchar",
          "primaryKey": false,
          "notNull": false
        },
        "cluster_loja": {
          "name": "cluster_loja",
          "type": "varchar",
          "primaryKey": false,
          "notNull": false
        },
        "cluster_rede": {
          "name": "cluster_rede",
          "type": "varchar",
          "primaryKey": false,
          "notNull": false
        },
        "segmentacao": {
          "name": "segmentacao",
          "type": "varchar",
          "primaryKey": false,
          "notNull": false
        },
        "sub_segmentacao": {
          "name": "sub_segmentacao",
          "type": "varchar",
          "primaryKey": false,
          "notNull": false
        },
        "categoria": {
          "name": "categoria",
          "type": "varchar",
          "primaryKey": false,
          "notNull": false
        },
        "migracao_asr": {
          "name": "migracao_asr",
          "type": "varchar",
          "primaryKey": false,
          "notNull": false
        },
        "programa_de_mercado": {
          "name": "programa_de_mercado",
          "type": "varchar",
          "primaryKey": false,
          "notNull": false
        },
        "status_loja": {
          "name": "status_loja",
          "type": "varchar",
          "primaryKey": false,
          "notNull": false
        },
        "loja_cd_normal_mista": {
          "name": "loja_cd_normal_mista",
          "type": "varchar",
          "primaryKey": false,
          "notNull": false
        },
        "eg_central": {
          "name": "eg_central",
          "type": "varchar",
          "primaryKey": false,
          "notNull": false
        },
        "eg_central_2": {
          "name": "eg_central_2",
          "type": "varchar",
          "primaryKey": false,
          "notNull": false
        },
        "mercado_nielsen": {
          "name": "mercado_nielsen",
          "type": "varchar",
          "primaryKey": false,
          "notNull": false
        },
        "leitura_scanntech": {
          "name": "leitura_scanntech",
          "type": "varchar",
          "primaryKey": false,
          "notNull": false
        },
        "leitura_neogrid": {
          "name": "leitura_neogrid",
          "type": "varchar",
          "primaryKey": false,
          "notNull": false
        },
        "dummhumby": {
          "name": "dummhumby",
          "type": "varchar",
          "primaryKey": false,
          "notNull": false
        },
        "shopping_brasil": {
          "name": "shopping_brasil",
          "type": "varchar",
          "primaryKey": false,
          "notNull": false
        },
        "tamanho_loja": {
          "name": "tamanho_loja",
          "type": "varchar",
          "primaryKey": false,
          "notNull": false
        },
        "cluster_trade": {
          "name": "cluster_trade",
          "type": "varchar",
          "primaryKey": false,
          "notNull": false
        },
        "kam_nac": {
          "name": "kam_nac",
          "type": "varchar",
          "primaryKey": false,
          "notNull": false
        },
        "diretor": {
          "name": "diretor",
          "type": "varchar",
          "primaryKey": false,
          "notNull": false
        },
        "cnpj_dup": {
          "name": "cnpj_dup",
          "type": "varchar",
          "primaryKey": false,
          "notNull": false
        },
        "latitude": {
          "name": "latitude",
          "type": "double precision",
          "primaryKey": false,
          "notNull": false
        },
        "longitude": {
          "name": "longitude",
          "type": "double precision",
          "primaryKey": false,
          "notNull": false
        }
      },
      "indexes": {},
      "foreignKeys": {},
      "compositePrimaryKeys": {},
      "uniqueConstraints": {}
    },
    "public.coleta_direta": {
      "name": "coleta_direta",
      "schema": "",
      "columns": {
        "id": {
          "name": "id",
          "type": "integer",
          "primaryKey": true,
          "notNull": true
        },
        "eg": {
          "name": "eg",
          "type": "varchar",
          "primaryKey": false,
          "notNull": false
        },
        "nome_usuario": {
          "name": "nome_usuario",
          "type": "varchar",
          "primaryKey": false,
          "notNull": false
        },
        "data_visita": {
          "name": "data_visita",
          "type": "timestamp",
          "primaryKey": false,
          "notNull": false
        },
        "materiais": {
          "name": "materiais",
          "type": "json",
          "primaryKey": false,
          "notNull": false
        },
        "fotos": {
          "name": "fotos",
          "type": "json",
          "primaryKey": false,
          "notNull": false
        }
      },
      "indexes": {},
      "foreignKeys": {},
      "compositePrimaryKeys": {},
      "uniqueConstraints": {}
    },
    "public.coleta_pdv": {
      "name": "coleta_pdv",
      "schema": "",
      "columns": {
        "id": {
          "name": "id",
          "type": "integer",
          "primaryKey": true,
          "notNull": true
        },
        "chave": {
          "name": "chave",
          "type": "varchar",
          "primaryKey": false,
          "notNull": false
        },
        "nome_usuario": {
          "name": "nome_usuario",
          "type": "varchar",
          "primaryKey": false,
          "notNull": false
        },
        "data_visita": {
          "name": "data_visita",
          "type": "timestamp",
          "primaryKey": false,
          "notNull": false
        },
        "cod_pdv": {
          "name": "cod_pdv",
          "type": "integer",
          "primaryKey": false,
          "notNull": true
        },
        "comercial": {
          "name": "comercial",
          "type": "varchar",
          "primaryKey": false,
          "notNull": false
        },
        "operação": {
          "name": "operação",
          "type": "varchar",
          "primaryKey": false,
          "notNull": true
        },
        "fachada": {
          "name": "fachada",
          "type": "varchar",
          "primaryKey": false,
          "notNull": false
        },
        "cardapio": {
          "name": "cardapio",
          "type": "varchar",
          "primaryKey": false,
          "notNull": false
        },
        "interior": {
          "name": "interior",
          "type": "varchar",
          "primaryKey": false,
          "notNull": false
        },
        "materiais": {
          "name": "materiais",
          "type": "json",
          "primaryKey": false,
          "notNull": false
        }
      },
      "indexes": {},
      "foreignKeys": {},
      "compositePrimaryKeys": {},
      "uniqueConstraints": {}
    },
    "public.pedidos_hub": {
      "name": "pedidos_hub",
      "schema": "",
      "columns": {
        "chave": {
          "name": "chave",
          "type": "varchar",
          "primaryKey": false,
          "notNull": true
        },
        "data_entrega": {
          "name": "data_entrega",
          "type": "varchar",
          "primaryKey": false,
          "notNull": false
        },
        "marca": {
          "name": "marca",
          "type": "varchar",
          "primaryKey": false,
          "notNull": false
        },
        "material": {
          "name": "material",
          "type": "varchar",
          "primaryKey": false,
          "notNull": false
        },
        "descricao": {
          "name": "descricao",
          "type": "varchar",
          "primaryKey": false,
          "notNull": false
        },
        "quantidade": {
          "name": "quantidade",
          "type": "varchar",
          "primaryKey": false,
          "notNull": false
        }
      },
      "indexes": {},
      "foreignKeys": {},
      "compositePrimaryKeys": {
        "pedidos_hub_chave_descricao_data_entrega_pk": {
          "name": "pedidos_hub_chave_descricao_data_entrega_pk",
          "columns": [
            "chave",
            "descricao",
            "data_entrega"
          ]
        }
      },
      "uniqueConstraints": {}
    },
    "public.volume": {
      "name": "volume",
      "schema": "",
      "columns": {
        "chave": {
          "name": "chave",
          "type": "varchar",
          "primaryKey": false,
          "notNull": true
        },
        "ano": {
          "name": "ano",
          "type": "integer",
          "primaryKey": false,
          "notNull": true
        },
        "mes": {
          "name": "mes",
          "type": "integer",
          "primaryKey": false,
          "notNull": true
        },
        "cerveja": {
          "name": "cerveja",
          "type": "double precision",
          "primaryKey": false,
          "notNull": false
        },
        "nab": {
          "name": "nab",
          "type": "double precision",
          "primaryKey": false,
          "notNull": false
        },
        "rgb": {
          "name": "rgb",
          "type": "double precision",
          "primaryKey": false,
          "notNull": false
        },
        "brahma": {
          "name": "brahma",
          "type": "double precision",
          "primaryKey": false,
          "notNull": false
        },
        "spaten": {
          "name": "spaten",
          "type": "double precision",
          "primaryKey": false,
          "notNull": false
        },
        "corona": {
          "name": "corona",
          "type": "double precision",
          "primaryKey": false,
          "notNull": false
        },
        "bud": {
          "name": "bud",
          "type": "double precision",
          "primaryKey": false,
          "notNull": false
        },
        "stella": {
          "name": "stella",
          "type": "double precision",
          "primaryKey": false,
          "notNull": false
        },
        "skol": {
          "name": "skol",
          "type": "double precision",
          "primaryKey": false,
          "notNull": false
        },
        "antarctica": {
          "name": "antarctica",
          "type": "double precision",
          "primaryKey": false,
          "notNull": false
        },
        "guarana": {
          "name": "guarana",
          "type": "double precision",
          "primaryKey": false,
          "notNull": false
        },
        "beats": {
          "name": "beats",
          "type": "double precision",
          "primaryKey": false,
          "notNull": false
        }
      },
      "indexes": {},
      "foreignKeys": {},
      "compositePrimaryKeys": {
        "volume_chave_ano_mes_pk": {
          "name": "volume_chave_ano_mes_pk",
          "columns": [
            "chave",
            "ano",
            "mes"
          ]
        }
      },
      "uniqueConstraints": {}
    }
  },
  "enums": {},
  "schemas": {},
  "sequences": {},
  "_meta": {
    "columns": {},
    "schemas": {},
    "tables": {}
  }
}